build123d_ease/__init__.py
build123d_ease/align.py
build123d_ease/ci_show.py
build123d_ease/fetch_faces.py
build123d_ease/math.py
build123d_ease/rotation.py
build123d_ease-0.2.0.0.dist-info/METADATA
build123d_ease-0.2.0.0.dist-info/WHEEL
build123d_ease-0.2.0.0.dist-info/licenses/LICENSE
build123d_ease-0.2.0.0.dist-info/RECORD
